{"version":1,"resource":"file:///home/andojas/Documents/dahu/src/app/app.component.html","entries":[{"id":"pRjw.html","timestamp":1717343256335},{"id":"aiHo.html","timestamp":1717350846716},{"id":"37lW.html","timestamp":1717502924340},{"id":"EG4e.html","timestamp":1717874680929},{"id":"IdTi.html","timestamp":1717874780089},{"id":"tgqp.html","timestamp":1717947474582},{"id":"umZ9.html","timestamp":1718009557921},{"id":"EYAs.html","timestamp":1718010831688},{"id":"1Epc.html","timestamp":1718105516066},{"id":"QsqL.html","timestamp":1718110138887},{"id":"xj49.html","timestamp":1718268506726},{"id":"jxVK.html","timestamp":1718270980915},{"id":"9TMv.html","timestamp":1718279215903},{"id":"trP9.html","timestamp":1718279604816},{"id":"0oOu.html","timestamp":1718279650213},{"id":"M9d4.html","timestamp":1718279865091},{"id":"3ASP.html","timestamp":1718280291811},{"id":"rM6B.html","timestamp":1718282786757},{"id":"u10E.html","timestamp":1718286001800},{"id":"cnIC.html","timestamp":1718286087299},{"id":"Tp4d.html","timestamp":1718286099199},{"id":"kW8I.html","timestamp":1718338272149},{"id":"BA3a.html","timestamp":1718339991861},{"id":"T4PU.html","timestamp":1718341928398},{"id":"EA37.html","timestamp":1718346019405},{"id":"NfhF.html","timestamp":1718347539469},{"id":"rY02.html","timestamp":1718364782495},{"id":"Ddru.html","timestamp":1718364796122},{"id":"TbMR.html","timestamp":1718364962010},{"id":"fr6D.html","timestamp":1718365289662},{"id":"8CE0.html","timestamp":1718365354830},{"id":"mVnn.html","timestamp":1718365593090},{"id":"Trwo.html","timestamp":1718366621123},{"id":"CYmf.html","timestamp":1718366707977},{"id":"Euu9.html","timestamp":1718367637778}]}