{"version":1,"resource":"file:///home/andojas/Documents/angular_tutorial/first-app/src/app/home/home.component.ts","entries":[{"id":"9YZ9.ts","timestamp":1715789142014},{"id":"sblO.ts","source":"Import HousingLocationComponent from '../housing-location/housing-location.component' on HomeComponent","timestamp":1715855807004},{"id":"Kwwh.ts","timestamp":1715857862658},{"id":"2xL6.ts","timestamp":1715929748221},{"id":"EOcn.ts","timestamp":1718369603752},{"id":"A5Zq.ts","timestamp":1718369738178},{"id":"OCEY.ts","timestamp":1718370175598}]}